client
contentstore
verified_fake
