Metadata-Version: 1.1
Name: django-messaging-contentstore
Version: 0.1.7
Summary: A RESTful API for managing collections of messaging content
Home-page: https://github.com/praekelt/django-messaging-contentstore
Author: Western Cape Labs
Author-email: devops@westerncapelabs.com
License: BSD
Platform: UNKNOWN
Classifier: Development Status :: 4 - Beta
Classifier: Intended Audience :: Developers
Classifier: License :: OSI Approved :: BSD License
Classifier: Operating System :: POSIX
Classifier: Programming Language :: Python
Classifier: Topic :: Software Development :: Libraries :: Python Modules
Classifier: Topic :: System :: Networking
